YongtaluoXieriji/README.md
YongtaluoXieriji/__init__.py
YongtaluoXieriji/__main__.py
YongtaluoXieriji/file.epub
YongtaluoXieriji/index.html
YongtaluoXieriji/css/__init__.py
YongtaluoXieriji/css/annotations.css
YongtaluoXieriji/css/main.css
YongtaluoXieriji/css/normalize.css
YongtaluoXieriji/css/popup.css
YongtaluoXieriji/font/__init__.py
YongtaluoXieriji/font/fontello.eot
YongtaluoXieriji/font/fontello.svg
YongtaluoXieriji/font/fontello.ttf
YongtaluoXieriji/font/fontello.woff
YongtaluoXieriji/img/__init__.py
YongtaluoXieriji/img/annotator-glyph-sprite.png
YongtaluoXieriji/img/annotator-icon-sprite.png
YongtaluoXieriji/img/apple-touch-icon.png
YongtaluoXieriji/img/cancelfullscreen.png
YongtaluoXieriji/img/close.png
YongtaluoXieriji/img/fullscreen.png
YongtaluoXieriji/img/loader.gif
YongtaluoXieriji/img/menu-icon.png
YongtaluoXieriji/img/save.png
YongtaluoXieriji/img/saved.png
YongtaluoXieriji/img/settings-s.png
YongtaluoXieriji/img/settings.png
YongtaluoXieriji/img/star.png
YongtaluoXieriji/js/__init__.py
YongtaluoXieriji/js/epub.js
YongtaluoXieriji/js/epub.min.js
YongtaluoXieriji/js/epub.min.map
YongtaluoXieriji/js/hooks.min.js
YongtaluoXieriji/js/hooks.min.map
YongtaluoXieriji/js/reader.js
YongtaluoXieriji/js/reader.js.map
YongtaluoXieriji/js/reader.min.js
YongtaluoXieriji/js/reader.min.map
YongtaluoXieriji/js/hooks/__init__.py
YongtaluoXieriji/js/hooks/extensions/__init__.py
YongtaluoXieriji/js/hooks/extensions/highlight.js
YongtaluoXieriji/js/libs/__init__.py
YongtaluoXieriji/js/libs/jquery.min.js
YongtaluoXieriji/js/libs/localforage.min.js
YongtaluoXieriji/js/libs/screenfull.js
YongtaluoXieriji/js/libs/screenfull.min.js
YongtaluoXieriji/js/libs/zip.min.js
YongtaluoXieriji/js/plugins/__init__.py
YongtaluoXieriji/js/plugins/hypothesis.js
YongtaluoXieriji/js/plugins/search.js
yongtaluo_xieriji-2022.9.29.0.dist-info/METADATA
yongtaluo_xieriji-2022.9.29.0.dist-info/WHEEL
yongtaluo_xieriji-2022.9.29.0.dist-info/entry_points.txt
yongtaluo_xieriji-2022.9.29.0.dist-info/top_level.txt
yongtaluo_xieriji-2022.9.29.0.dist-info/RECORD
